rimecard/__init__.py
rimecard-0.1.3.dist-info/METADATA
rimecard-0.1.3.dist-info/WHEEL
rimecard-0.1.3.dist-info/entry_points.txt
rimecard-0.1.3.dist-info/licenses/LICENSE
rimecard-0.1.3.dist-info/RECORD
