Metadata-Version: 2.4
Name: rimecard
Version: 0.1.3
Summary: Extract vcf vcard contacts to rime pinyin dictionary.
Project-URL: homepage, https://github.com/darkclip/rimecard
Project-URL: repository, https://github.com/darkclip/rimecard
Project-URL: documentation, https://github.com/darkclip/rimecard
Author-email: darkclip <darkclip@hanv.dev>
License-Expression: MIT
License-File: LICENSE
Keywords: dict,dictionary,pinyin,rime,vcard,vcf
Requires-Python: >=3.8
Requires-Dist: chardet>=5.2.0
Requires-Dist: pypinyin>=0.54.0
